<?xml version="1.0" encoding="UTF-8"?>
<AmazonEnvelope xmlns:xsi="http://www.w3.org/2001/XMLSchema-instance" xsi:noNamespaceSchemaLocation="amzn-envelope.xsd">
	<Header>
		<DocumentVersion>1.02</DocumentVersion>
		<MerchantIdentifier>A2O70136OXEC74</MerchantIdentifier>
	</Header>
	<MessageType>ProcessingReport</MessageType>
	<Message>
		<MessageID>1</MessageID>
		<ProcessingReport>
			<DocumentTransactionID>51890018360</DocumentTransactionID>
			<StatusCode>Complete</StatusCode>
			<ProcessingSummary>
				<MessagesProcessed>583</MessagesProcessed>
				<MessagesSuccessful>581</MessagesSuccessful>
				<MessagesWithError>2</MessagesWithError>
				<MessagesWithWarning>0</MessagesWithWarning>
			</ProcessingSummary>
			<Result>
				<MessageID>142</MessageID>
				<ResultCode>Error</ResultCode>
				<ResultMessageCode>20000</ResultMessageCode>
				<ResultDescription>We could not access the media at URL http://ldimg.ldkjmy.com/image/k8o5t6zs_45450mcfc3h55e8adb99851ec.jpg. The download request timed out. Ensure that the URL is correct and the media is publicly accessible.</ResultDescription>
				<AdditionalInfo>
					<SKU>YXYLD-271586158470-11-HE</SKU>
				</AdditionalInfo>
			</Result>
			<Result>
				<MessageID>267</MessageID>
				<ResultCode>Error</ResultCode>
				<ResultMessageCode>20000</ResultMessageCode>
				<ResultDescription>We could not access the media at URL http://ldimg.ldkjmy.com/image/k8o62pl4_1cn91mk4p8wl5e8add552b70a.jpg. The download request timed out. Ensure that the URL is correct and the media is publicly accessible.</ResultDescription>
				<AdditionalInfo>
					<SKU>YXYLD-271586158893-8-HE</SKU>
				</AdditionalInfo>
			</Result>
		</ProcessingReport>
	</Message>
</AmazonEnvelope>